{
  "id": "b47ac923-459f-4e85-955d-ccf074726a8c",
  "extra": {
    "ds": {
      "scale": 1.6105100000000008,
      "offset": [335.5460782281936, 27.821689642117917]
    },
    "reroutes": null,
    "frontendVersion": "1.23.4"
  },
  "links": [
    [9, 8, 0, 9, 0, "IMAGE"],
    [10, 11, 0, 6, 0, "CLIP"],
    [12, 10, 0, 8, 1, "VAE"],
    [19, 16, 0, 13, 2, "SAMPLER"],
    [20, 17, 0, 13, 3, "SIGMAS"],
    [23, 5, 0, 13, 4, "LATENT"],
    [24, 13, 0, 8, 0, "LATENT"],
    [30, 22, 0, 13, 1, "GUIDER"],
    [37, 25, 0, 13, 0, "NOISE"],
    [38, 12, 0, 17, 0, "MODEL"],
    [39, 12, 0, 22, 0, "MODEL"],
    [40, 6, 0, 22, 1, "CONDITIONING"]
  ],
  "nodes": [
    {
      "id": 13,
      "pos": [842, 215],
      "mode": 0,
      "size": [355.20001220703125, 106],
      "type": "SamplerCustomAdvanced",
      "flags": {},
      "order": 10,
      "inputs": [
        {
          "dir": null,
          "pos": null,
          "link": 37,
          "name": "noise",
          "type": "NOISE",
          "label": null,
          "shape": null,
          "locked": null,
          "color_on": null,
          "color_off": null,
          "removable": null,
          "nameLocked": null
        },
        {
          "dir": null,
          "pos": null,
          "link": 30,
          "name": "guider",
          "type": "GUIDER",
          "label": null,
          "shape": null,
          "locked": null,
          "color_on": null,
          "color_off": null,
          "removable": null,
          "nameLocked": null
        },
        {
          "dir": null,
          "pos": null,
          "link": 19,
          "name": "sampler",
          "type": "SAMPLER",
          "label": null,
          "shape": null,
          "locked": null,
          "color_on": null,
          "color_off": null,
          "removable": null,
          "nameLocked": null
        },
        {
          "dir": null,
          "pos": null,
          "link": 20,
          "name": "sigmas",
          "type": "SIGMAS",
          "label": null,
          "shape": null,
          "locked": null,
          "color_on": null,
          "color_off": null,
          "removable": null,
          "nameLocked": null
        },
        {
          "dir": null,
          "pos": null,
          "link": 23,
          "name": "latent_image",
          "type": "LATENT",
          "label": null,
          "shape": null,
          "locked": null,
          "color_on": null,
          "color_off": null,
          "removable": null,
          "nameLocked": null
        }
      ],
      "outputs": [
        {
          "dir": null,
          "pos": null,
          "name": "output",
          "type": "LATENT",
          "label": null,
          "links": [24],
          "shape": null,
          "locked": null,
          "color_on": null,
          "color_off": null,
          "removable": null,
          "nameLocked": null,
          "slot_index": 0
        },
        {
          "dir": null,
          "pos": null,
          "name": "denoised_output",
          "type": "LATENT",
          "label": null,
          "links": null,
          "shape": null,
          "locked": null,
          "color_on": null,
          "color_off": null,
          "removable": null,
          "nameLocked": null,
          "slot_index": null
        }
      ],
      "properties": {
        "Node name for S&R": "SamplerCustomAdvanced"
      },
      "showAdvanced": null,
      "widgets_values": []
    },
    {
      "id": 5,
      "pos": [473, 450],
      "mode": 0,
      "size": [315, 106],
      "type": "EmptyLatentImage",
      "flags": {},
      "order": 0,
      "inputs": [],
      "outputs": [
        {
          "dir": null,
          "pos": null,
          "name": "LATENT",
          "type": "LATENT",
          "label": null,
          "links": [23],
          "shape": null,
          "locked": null,
          "color_on": null,
          "color_off": null,
          "removable": null,
          "nameLocked": null,
          "slot_index": 0
        }
      ],
      "properties": {
        "Node name for S&R": "EmptyLatentImage"
      },
      "showAdvanced": null,
      "widgets_values": [1024, 1024, 1]
    },
    {
      "id": 22,
      "pos": [559, 125],
      "mode": 0,
      "size": [241.79998779296875, 46],
      "type": "BasicGuider",
      "flags": {},
      "order": 9,
      "inputs": [
        {
          "dir": null,
          "pos": null,
          "link": 39,
          "name": "model",
          "type": "MODEL",
          "label": null,
          "shape": null,
          "locked": null,
          "color_on": null,
          "color_off": null,
          "removable": null,
          "nameLocked": null
        },
        {
          "dir": null,
          "pos": null,
          "link": 40,
          "name": "conditioning",
          "type": "CONDITIONING",
          "label": null,
          "shape": null,
          "locked": null,
          "color_on": null,
          "color_off": null,
          "removable": null,
          "nameLocked": null
        }
      ],
      "outputs": [
        {
          "dir": null,
          "pos": null,
          "name": "GUIDER",
          "type": "GUIDER",
          "label": null,
          "links": [30],
          "shape": null,
          "locked": null,
          "color_on": null,
          "color_off": null,
          "removable": null,
          "nameLocked": null,
          "slot_index": 0
        }
      ],
      "properties": {
        "Node name for S&R": "BasicGuider"
      },
      "showAdvanced": null,
      "widgets_values": []
    },
    {
      "id": 16,
      "pos": [470, 749],
      "mode": 0,
      "size": [315, 58],
      "type": "KSamplerSelect",
      "flags": {},
      "order": 1,
      "inputs": [],
      "outputs": [
        {
          "dir": null,
          "pos": null,
          "name": "SAMPLER",
          "type": "SAMPLER",
          "label": null,
          "links": [19],
          "shape": null,
          "locked": null,
          "color_on": null,
          "color_off": null,
          "removable": null,
          "nameLocked": null,
          "slot_index": null
        }
      ],
      "properties": {
        "Node name for S&R": "KSamplerSelect"
      },
      "showAdvanced": null,
      "widgets_values": ["euler"]
    },
    {
      "id": 8,
      "pos": [1248, 192],
      "mode": 0,
      "size": [210, 46],
      "type": "VAEDecode",
      "flags": {},
      "order": 11,
      "inputs": [
        {
          "dir": null,
          "pos": null,
          "link": 24,
          "name": "samples",
          "type": "LATENT",
          "label": null,
          "shape": null,
          "locked": null,
          "color_on": null,
          "color_off": null,
          "removable": null,
          "nameLocked": null
        },
        {
          "dir": null,
          "pos": null,
          "link": 12,
          "name": "vae",
          "type": "VAE",
          "label": null,
          "shape": null,
          "locked": null,
          "color_on": null,
          "color_off": null,
          "removable": null,
          "nameLocked": null
        }
      ],
      "outputs": [
        {
          "dir": null,
          "pos": null,
          "name": "IMAGE",
          "type": "IMAGE",
          "label": null,
          "links": [9],
          "shape": null,
          "locked": null,
          "color_on": null,
          "color_off": null,
          "removable": null,
          "nameLocked": null,
          "slot_index": 0
        }
      ],
      "properties": {
        "Node name for S&R": "VAEDecode"
      },
      "showAdvanced": null,
      "widgets_values": []
    },
    {
      "id": 17,
      "pos": [468, 867],
      "mode": 0,
      "size": [315, 106],
      "type": "BasicScheduler",
      "flags": {},
      "order": 7,
      "inputs": [
        {
          "dir": null,
          "pos": null,
          "link": 38,
          "name": "model",
          "type": "MODEL",
          "label": null,
          "shape": null,
          "locked": null,
          "color_on": null,
          "color_off": null,
          "removable": null,
          "nameLocked": null
        }
      ],
      "outputs": [
        {
          "dir": null,
          "pos": null,
          "name": "SIGMAS",
          "type": "SIGMAS",
          "label": null,
          "links": [20],
          "shape": null,
          "locked": null,
          "color_on": null,
          "color_off": null,
          "removable": null,
          "nameLocked": null,
          "slot_index": null
        }
      ],
      "properties": {
        "Node name for S&R": "BasicScheduler"
      },
      "showAdvanced": null,
      "widgets_values": ["simple", 20, 1]
    },
    {
      "id": 25,
      "pos": [470, 611],
      "mode": 0,
      "size": [315, 82],
      "type": "RandomNoise",
      "flags": {},
      "order": 2,
      "inputs": [],
      "outputs": [
        {
          "dir": null,
          "pos": null,
          "name": "NOISE",
          "type": "NOISE",
          "label": null,
          "links": [37],
          "shape": null,
          "locked": null,
          "color_on": null,
          "color_off": null,
          "removable": null,
          "nameLocked": null,
          "slot_index": null
        }
      ],
      "properties": {
        "Node name for S&R": "RandomNoise"
      },
      "showAdvanced": null,
      "widgets_values": [417264191485848, "randomize"]
    },
    {
      "id": 10,
      "pos": [864, 384],
      "mode": 0,
      "size": [315, 58],
      "type": "VAELoader",
      "flags": {},
      "order": 3,
      "inputs": [],
      "outputs": [
        {
          "dir": null,
          "pos": null,
          "name": "VAE",
          "type": "VAE",
          "label": null,
          "links": [12],
          "shape": null,
          "locked": null,
          "color_on": null,
          "color_off": null,
          "removable": null,
          "nameLocked": null,
          "slot_index": 0
        }
      ],
      "properties": {
        "Node name for S&R": "VAELoader"
      },
      "showAdvanced": null,
      "widgets_values": ["flux/ae.sft"]
    },
    {
      "id": 9,
      "pos": [1488, 192],
      "mode": 0,
      "size": [673.9125366210938, 721.863525390625],
      "type": "SaveImage",
      "flags": {},
      "order": 12,
      "inputs": [
        {
          "dir": null,
          "pos": null,
          "link": 9,
          "name": "images",
          "type": "IMAGE",
          "label": null,
          "shape": null,
          "locked": null,
          "color_on": null,
          "color_off": null,
          "removable": null,
          "nameLocked": null
        }
      ],
      "outputs": [],
      "properties": {
        "Node name for S&R": "SaveImage"
      },
      "showAdvanced": null,
      "widgets_values": ["1111"]
    },
    {
      "id": 6,
      "pos": [375, 221],
      "mode": 0,
      "size": [422.84503173828125, 164.31304931640625],
      "type": "CLIPTextEncode",
      "flags": {},
      "order": 8,
      "inputs": [
        {
          "dir": null,
          "pos": null,
          "link": 10,
          "name": "clip",
          "type": "CLIP",
          "label": null,
          "shape": null,
          "locked": null,
          "color_on": null,
          "color_off": null,
          "removable": null,
          "nameLocked": null
        }
      ],
      "outputs": [
        {
          "dir": null,
          "pos": null,
          "name": "CONDITIONING",
          "type": "CONDITIONING",
          "label": null,
          "links": [40],
          "shape": null,
          "locked": null,
          "color_on": null,
          "color_off": null,
          "removable": null,
          "nameLocked": null,
          "slot_index": 0
        }
      ],
      "properties": {
        "Node name for S&R": "CLIPTextEncode"
      },
      "showAdvanced": null,
      "widgets_values": [
        "n old tv with the word \"FLUX\" on it, sitting in an abandoned workshop environment, created in Unreal Engine 5 with Octane render in the style of ArtStation."
      ]
    },
    {
      "id": 12,
      "pos": [-2, 129],
      "mode": 0,
      "size": [336.9091796875, 82.82049560546875],
      "type": "UNETLoader",
      "flags": {},
      "order": 4,
      "inputs": [],
      "outputs": [
        {
          "dir": null,
          "pos": null,
          "name": "MODEL",
          "type": "MODEL",
          "label": null,
          "links": [38, 39],
          "shape": null,
          "locked": null,
          "color_on": null,
          "color_off": null,
          "removable": null,
          "nameLocked": null,
          "slot_index": 0
        }
      ],
      "properties": {
        "Node name for S&R": "UNETLoader"
      },
      "showAdvanced": null,
      "widgets_values": ["flux/flux1-schnell.sft", "fp8_e4m3fn"]
    },
    {
      "id": 26,
      "pos": [-246, 131],
      "mode": 0,
      "size": [210, 257.4190673828125],
      "type": "Note",
      "color": "#432",
      "flags": {},
      "order": 5,
      "inputs": [],
      "bgcolor": "#653",
      "outputs": [],
      "properties": {
        "text": ""
      },
      "showAdvanced": null,
      "widgets_values": [
        "When launching a RunComfy medium-sized machine, use the settings: checkpoint (flux1_schnell, fp8) and clip (t5_xxl_fp8), or it will run out of memory.\n\nWhen launching a RunComfy large-sized or above machine, you can choose a larger model and fp16 for better result: checkpoint (flux1_dev, default) and clip (t5_xxl_fp16)."
      ]
    },
    {
      "id": 11,
      "pos": [6, 279],
      "mode": 0,
      "size": [352.1158447265625, 130],
      "type": "DualCLIPLoader",
      "flags": {
        "collapsed": false
      },
      "order": 6,
      "inputs": [],
      "outputs": [
        {
          "dir": null,
          "pos": null,
          "name": "CLIP",
          "type": "CLIP",
          "label": null,
          "links": [10],
          "shape": null,
          "locked": null,
          "color_on": null,
          "color_off": null,
          "removable": null,
          "nameLocked": null,
          "slot_index": 0
        }
      ],
      "properties": {
        "Node name for S&R": "DualCLIPLoader"
      },
      "showAdvanced": null,
      "widgets_values": [
        "sd3m/t5xxl_fp8_e4m3fn.safetensors",
        "sd3m/clip_l.safetensors",
        "flux",
        "default"
      ]
    }
  ],
  "config": {},
  "groups": [],
  "version": 0.4,
  "revision": 0,
  "last_link_id": 40,
  "last_node_id": 26,
  "floatingLinks": null
}
